evojax/__init__.py
evojax/obs_norm.py
evojax/sim_mgr.py
evojax/trainer.py
evojax/util.py
evojax/version.py
evojax/algo/__init__.py
evojax/algo/ars.py
evojax/algo/ars_native.py
evojax/algo/base.py
evojax/algo/cma_evosax.py
evojax/algo/cma_jax.py
evojax/algo/cma_wrapper.py
evojax/algo/crfmnes.py
evojax/algo/fcrfmc.py
evojax/algo/fpgpec.py
evojax/algo/iamalgam.py
evojax/algo/map_elites.py
evojax/algo/open_es.py
evojax/algo/pgpe.py
evojax/algo/sep_cma_es.py
evojax/algo/simple_ga.py
evojax/policy/__init__.py
evojax/policy/base.py
evojax/policy/convnet.py
evojax/policy/mlp.py
evojax/policy/mlp_pi.py
evojax/policy/seq2seq.py
evojax/task/__init__.py
evojax/task/base.py
evojax/task/brax_task.py
evojax/task/cartpole.py
evojax/task/flocking.py
evojax/task/ma_waterworld.py
evojax/task/mdkp.py
evojax/task/mnist.py
evojax/task/procgen_task.py
evojax/task/seq2seq.py
evojax/task/slimevolley.py
evojax/task/waterworld.py
evojax-0.2.17.dist-info/LICENSE
evojax-0.2.17.dist-info/METADATA
evojax-0.2.17.dist-info/WHEEL
evojax-0.2.17.dist-info/dependency_links.txt
evojax-0.2.17.dist-info/top_level.txt
evojax-0.2.17.dist-info/RECORD
