Metadata-Version: 2.1
Name: evojax
Version: 0.2.17
Summary: EvoJAX: Hardware-accelerated Neuroevolution.
Home-page: https://github.com/google/evojax
Author: Google
Author-email: evojax-dev@google.com
License: Apache 2.0
Classifier: Intended Audience :: Developers
Classifier: Intended Audience :: Science/Research
Classifier: License :: OSI Approved :: Apache Software License
Classifier: Topic :: Scientific/Engineering :: Artificial Intelligence
Classifier: Programming Language :: Python :: 3
Classifier: Programming Language :: Python :: 3.8
Classifier: Programming Language :: Python :: 3.9
Classifier: Programming Language :: Python :: 3.10
Requires-Python: >=3.8
License-File: LICENSE
Requires-Dist: flax
Requires-Dist: jax >=0.2.17
Requires-Dist: jaxlib >=0.1.65
Requires-Dist: Pillow
Requires-Dist: cma
Requires-Dist: matplotlib
Requires-Dist: pyyaml
Provides-Extra: extra
Requires-Dist: evosax ; extra == 'extra'
Requires-Dist: torchvision ; extra == 'extra'
Requires-Dist: pandas ; extra == 'extra'
Requires-Dist: procgen ; extra == 'extra'
Requires-Dist: brax ; extra == 'extra'
